STLFLib/EDA.py
STLFLib/__init__.py
STLFLib/core.py
STLFLib/dependency.py
STLFLib/preprocessing.py
STLFLib/serviceDB.py
STLFLib/validating.py
stlflib-1.0.2.dist-info/METADATA
stlflib-1.0.2.dist-info/WHEEL
stlflib-1.0.2.dist-info/top_level.txt
stlflib-1.0.2.dist-info/RECORD
