Metadata-Version: 2.1
Name: stlflib
Version: 1.0.2
Summary: Short-Term Forecasting of Regional Electrical Load Based on CatBoost Model
Home-page: https://github.com/caapel/ForecastPowerEnergy
Author: caapel
Author-email: caapel@mail.ru
License: KSPEU License
Project-URL: GitHub, https://github.com/caapel/ForecastPowerEnergy
Keywords: STLF
Classifier: Programming Language :: Python :: 3.10
Classifier: License :: Other/Proprietary License
Classifier: Operating System :: OS Independent
Requires-Python: >=3.10
Requires-Dist: ephem
Requires-Dist: requests
Requires-Dist: beautifulsoup4
Requires-Dist: tqdm
Requires-Dist: numpy
Requires-Dist: pandas
Requires-Dist: seaborn
Requires-Dist: matplotlib
Requires-Dist: catboost
Requires-Dist: graphviz
Requires-Dist: scikit-learn
